pymatrices/__init__.py
pymatrices-0.1.1.dist-info/LICENSE
pymatrices-0.1.1.dist-info/METADATA
pymatrices-0.1.1.dist-info/WHEEL
pymatrices-0.1.1.dist-info/top_level.txt
pymatrices-0.1.1.dist-info/RECORD
