Metadata-Version: 2.1
Name: pymatrices
Version: 0.1.1
Summary: A Python 3.x package to implement Matrices and almost all its Properties
Home-page: UNKNOWN
Author: Programmin-in-Python (MK)
Author-email: <kalanithi6014@gmail.com>
License: UNKNOWN
Project-URL: HomePage, https://github.com/Programmin-in-Python/PyMatrices
Keywords: python3,matrices,eigenvalues,Mathematics,mathematics,maths,pymatrices,PyMatrices,eigenvectors,2D matrix
Platform: UNKNOWN
Classifier: Development Status :: 5 - Production/Stable
Classifier: Intended Audience :: Science/Research
Classifier: License :: OSI Approved :: MIT License
Classifier: Natural Language :: English
Classifier: Operating System :: Unix
Classifier: Operating System :: MacOS :: MacOS X
Classifier: Operating System :: Microsoft :: Windows
Classifier: Operating System :: OS Independent
Classifier: Programming Language :: Python :: 3 :: Only
Classifier: Programming Language :: Python :: 3
Classifier: Topic :: Education
Classifier: Topic :: Scientific/Engineering :: Mathematics
Classifier: Topic :: Scientific/Engineering :: Physics
Requires-Python: >=3
